ruscorpora/__init__.py
ruscorpora-0.10.0.dist-info/WHEEL
ruscorpora-0.10.0.dist-info/METADATA
ruscorpora-0.10.0.dist-info/RECORD
