Metadata-Version: 2.1
Name: ruscorpora
Version: 0.10.0
Summary: Links to https://github.com/kunansy/rnc
Home-page: https://kunansy.github.io/RNC/
License: MIT
Keywords: api,corpus,ruscorpora,linguistics,russian-national-corpus
Author: kunansy
Author-email: kolobov.kirill@list.ru
Requires-Python: >=3.7,<4.0
Classifier: Development Status :: 5 - Production/Stable
Classifier: Intended Audience :: Education
Classifier: Intended Audience :: Science/Research
Classifier: License :: OSI Approved :: MIT License
Classifier: Natural Language :: Bulgarian
Classifier: Natural Language :: Chinese (Simplified)
Classifier: Natural Language :: Chinese (Traditional)
Classifier: Natural Language :: Czech
Classifier: Natural Language :: English
Classifier: Natural Language :: Finnish
Classifier: Natural Language :: French
Classifier: Natural Language :: German
Classifier: Natural Language :: Italian
Classifier: Natural Language :: Latvian
Classifier: Natural Language :: Lithuanian
Classifier: Natural Language :: Polish
Classifier: Natural Language :: Spanish
Classifier: Natural Language :: Swedish
Classifier: Natural Language :: Ukrainian
Classifier: Operating System :: OS Independent
Classifier: Programming Language :: Python
Classifier: Programming Language :: Python :: 3
Classifier: Programming Language :: Python :: 3 :: Only
Classifier: Programming Language :: Python :: 3.10
Classifier: Programming Language :: Python :: 3.7
Classifier: Programming Language :: Python :: 3.8
Classifier: Programming Language :: Python :: 3.9
Classifier: Topic :: Education
Classifier: Topic :: Scientific/Engineering
Requires-Dist: rnc (>=0.10.0,<0.11.0)
Project-URL: Bug Tracker, https://github.com/kunansy/RNC/issues
Project-URL: Changelog, https://github.com/kunansy/RNC/blob/master/CHANGELOG.md
Project-URL: Documentation, https://kunansy.github.io/RNC/
Project-URL: Funding, https://paypal.me/ansth
Project-URL: Repository, https://github.com/kunansy/RNC/
